issctl/__init__.py
issctl/lib/__init__.py
issctl/lib/issue.py
issctl/lib/issue_manager.py
issctl/main.py
issctl-0.1.0.dist-info/entry_points.txt
issctl-0.1.0.dist-info/WHEEL
issctl-0.1.0.dist-info/METADATA
issctl-0.1.0.dist-info/RECORD
